{
  "url": "http://vsticker.education.gov.in",
  "title": "Shastri Bhawan : Vehicle Parking Label Application",
  "meta_description": "",
  "meta_keywords": "",
  "text_content": "Shastri Bhawan : Vehicle Parking Label Application Vehicle Parking Label Application LOGIN (Only for MOE Govt. Employees) Vehicle User Admin User Personal Vehicle Parking Label 2026 will start from 1st January 2026 (For Permanent Staff of MoE Only) This site is designed, developed, hosted and maintained by National Informatics Centre (NIC) Department of Electronics & Information Technology, Ministry of Communications & Information Technology Technology Government of India.",
  "canonical_url": null,
  "category": "government",
  "country": "IN",
  "crawl_date": "2026-03-22T16:27:56.730469",
  "links": [],
  "image_urls": [
    "http://vsticker.education.gov.in/images/logo_2.png",
    "http://vsticker.education.gov.in/images/g20-logo.png",
    "http://vsticker.education.gov.in/GenerateCaptcha.aspx?639097934281783648",
    "http://vsticker.education.gov.in/images/nic-logo.png",
    "http://vsticker.education.gov.in/images/shastri-bhawan.jpg"
  ],
  "headings": {
    "h1": [],
    "h2": [],
    "h3": [],
    "h4": [],
    "h5": [],
    "h6": []
  },
  "word_count": 67,
  "link_count": 0,
  "image_count": 5
}