{
  "url": "https://www.tumblr.com",
  "title": "Trending topics on Tumblr",
  "meta_description": "Explore trending topics on Tumblr. See all of the GIFs, fan art, and general conversation about the internet’s favorite things.",
  "meta_keywords": "",
  "text_content": "Trending Staff Picks Videos More",
  "canonical_url": "https://www.tumblr.com/explore/trending",
  "category": "social_media",
  "country": "US",
  "crawl_date": "2026-03-22T16:24:28.214382",
  "links": [
    "https://www.tumblr.com/explore/staff-picks",
    "https://www.tumblr.com/explore/trending",
    "https://www.tumblr.com/explore/video"
  ],
  "image_urls": [],
  "headings": {
    "h1": [],
    "h2": [],
    "h3": [],
    "h4": [],
    "h5": [],
    "h6": []
  },
  "word_count": 5,
  "link_count": 3,
  "image_count": 0
}