{
  "url": "http://www.iitm.ac.in/",
  "title": "Indian Institute of Technology Madras",
  "meta_description": "Indian Institute of Technology Madras is Best Institute for higher education in India. It is a public technical and research university located in Chennai",
  "meta_keywords": "",
  "text_content": "Announcements DDWS Innovation Challenge 2025 - 26 application portal open now Summer Fellowship 2026 Vigilance Awareness Week - 27th October to 2nd November, 2025 Vigilance Awareness Week - 27th October to 2nd November, 2025 79th Independence Day Celebrations - Live streaming P M VIDYALAXMI NODAL BANK LEAFLET 62nd Convocation 66th Institute Day 2025 - Live Streaming Rolling Advertisement No IITM/R/3/2025 Dated 11.04.2025 visit https://facapp.iitm.ac.in/ for application The Crouching Tiger – A report on Startups in Textiles PG Programme Admissions 2025 UG Programme Admissions 2025 AskIITM.com for JoSAA 2023 doubts & queries Admissions to 4 year Medical Science and Engineering Program International Interdisciplinary Master’s Program (I2MP) No. 1 for 5 Years Running... The Champions of Technology Incubating Minds Catalyzing Careers The Best of the Best No. 1 for 9 Years Running... News View All IIT Madras honours six educators with First Principles Teachers Award 2026 Indian Institute of Technology Madras (IIT Madras) honoured six outstanding… 9 Mar 2026 Press Release IIT Madras launches Postgraduate Diploma in Manufacturing Analytics for Industry… Indian Institute of Technology Madras (IIT Madras) is launching a… 5 Mar 2026 Press Release IIT Madras study charts renewable energy pathway for Zero-Emission Trucking An Indian Institute of Technology Madras (IIT Madras) study has come out… 26 Feb 2026 Press Release Recent Calendar 18 Apr 03:30 PM Spectrum Inspired Low-light Image Translation for Saliency Detection Saliency detection methods are crucial in various practical applications,… Study @ IITM Online BSc Programme A completely online programme aimed at creating a trained programmer, proficient in application development, data sciences and machine learning. Undergraduate Programmes The B Tech programmes at IIT Madras encourage interdisciplinary studies and caters to the changing scientific and technological needs. Postgraduate Programmes The postgraduate programmes are specialized programmes aimed at engaging the students in learning, teaching and research. Research Programmes IIT Madras is internationally renowned for the quality and diversity of its research; and&nbsp;opportunities of active research in frontier areas. International Masters’ Program The I2MP courses are aimed at bringing&nbsp;students with diverse interests to the IIT Madras campus, and provide them the benefit of the rich teaching and research environment at IITM. Exchange Programmes IIT Madras encourages collaborations with foreign universities through student exchange programmes and visiting faculty. Joint Degree Programmes IIT Madras is at the forefront of collaborative learning and research having Joint Ph.D. programs with 20 world-class institutions. Research Highlights View all Research Highlights How cool motorbikes are choking Indian cities! In a new study, the scientists from IIT Madras show that the polluting… Why getting too personal may harm e-Commerce! Gone are the days when the only way to buy something was to go to a… Centres Healthcare Technology Innovation Centre (HTIC) The Healthcare Technology Innovation Centre (HTIC) is a… Centre for Technology and Policy (CTaP) The Centre for Technology and Policy (CTaP) provides analyses and… National Technology Centre for Ports, Waterways and Coasts (NTCPWC) The National Technology Centre for Ports, Waterways &amp; Coasts (… IITM China Studies Centre IITM China Studies Centre was established in April 2011 with a view to… Advanced Manufacturing Technology Development Centre (AMTDC) The Advanced Manufacturing Technology Development Centre (AMTDC) is a… National Centre for Combustion Research and Development (NCCRD) Founded by the Combustion Institute – Indian Section and supported by… National Cancer Tissue Biobank (NCTB) National Cancer Tissue Biobank (NCTB) is a state-of-the-art non-profit… Centre of Excellence in Wireless Technology (CEWiT) Set up with support from the Ministry of Communication and IT and the… Centre for Computational Brain Research The Centre for Computational Brain Research (CCBR) is a high-level… Centre for Railway Research The Centre for Railway Research (CRR) was set up in 2015 to develop a… Centre for NEMS and Nanophotonics (CNNP) The Centre for Nanoelectromechanical Systems (NEMS) and Nanophotonics… International Centre for Clean Water (ICCW) Established in 2018 with the objective of creating water professionals… TTK Center for Rehabilitation Research and Device Development (R2D2) R2D2 is the TTK Center for Rehabilitation Research and Device… Indo-German Centre for Sustainability Indo German Centre for Sustainability (IGCS) was established in 2010… Robert Bosch Centre for Data Science and Artificial Intelligence Founded in 2017, the Robert Bosch Centre for Data Science and… Departments Aerospace Engineering Established in 1969, the Department of Aerospace Engineering stands at the forefront of fundamental and applied… Applied Mechanics & Biomedical Engineering Since its inception in 1959, the Department of Applied Mechanics&nbsp;&amp; Biomedical Engineering has grown into a… Biotechnology The Department of Biotechnology was founded in 2004 with a strong interdisciplinary research and teaching base in… Chemical Engineering Aiming to be a global centre of academic and research excellence in chemical engineering sciences and technology,… Chemistry The Department of Chemistry is one of the first to function after IIT Madras was founded in 1959. Civil Engineering Since its inception in 1959, the Department of Civil Engineering has grown into a full-fledged department with… Computer Science & Engineering Conceived in 1973 with the acquisition of an IBM System/370 (one of the most powerful computers in India at that… Electrical Engineering The Department of Electrical Engineering is actively involved with research from absolute fundamentals and component… Engineering Design Established in 2006, the Department of Engineering Design at IIT Madras is the first of its kind in India. Humanities and Social Sciences The Department of Humanities and Social Sciences (HSS) is one of the oldest departments at IIT Madras. Management Studies The Department of Management Studies was established in 2004 to accommodate the popular Master in Business… Mathematics Established in 1959 along with the Institute, the Department of Mathematics has taken the responsibility of teaching… Mechanical Engineering The Department of Mechanical Engineering is the largest of its kind in the country and one of the largest in Asia.… Metallurgical and Materials Engineering The Department of Metallurgical and Materials Engineering is one of the oldest having been started in the same year… Ocean Engineering Originally conceived as the Ocean Engineering Centre (OEC) in 1977, the Department of Ocean Engineering (DOE) has… Physics The Department of Physics is amongst the largest physics departments in the country in terms of the number of… Consultancy & Innovation Industrial Consultancy The Centre for Industrial Consultancy and Sponsored Research (ICSR) was sta... Incubation Cell The IITM Incubation Cell (IITMIC) is India’s leading Deep-tech Startup hub.... IIT Madras Bioincubator The IITM Bioincubator works to foster Indian biotech innovation and entrepr... IITM Research Park IIT Madras Research Park (IITMRP), India's first university-based research ... Technology Transfer IIT Madras has an array of technologies / IPR developed through Research an... Gopalakrishnan-Deshpande Centre Established in 2017 the Gopalakrishnan Deshpande Center for Innovation &amp... IITM Pravartak IITM Pravartak Technologies Foundation is a section 08 company housing the ... IIT Madras by the Numbers 2,105 Undergraduate Students 4,112 Postgraduate Students 746 MS Research Scholars 2,963 PhD Research Scholars 591 Faculty 677 Staff 146 Patents 829 Projects Message from the Director Greetings to all! It is with great pleasure that I write this in the capacity of the Director of this prestigious institute. I thank all the faculty members, students, and staff of IIT Madras for their continuing efforts every day in keeping this distinguished institute of national importance at the top of the ranking scales, year after year. The role of a campus in ensuring quality learning is of great significance and IIT Madras, which already has a world-class campus, will now ensure it is further infused with the spirit of inclusivity, by celebrating the pluralism of cultures, nationalities, and personalities in a global world. We envision our campus to reflect the ethos of innovation, entrepreneurship, and dynamism of spirit. Each IITian should foster an endless, restless quest to look for solutions to real-world problems thereby contributing to the society we live in and helping our nation truly be “atma-nirbhar” (self-reliant). I envisage the good presence of IIT Madras to be perceptibly felt far beyond the walls of our campus, wherein every corner of our country and thereby the world, is able to tangibly feel the difference we intend to make to society with our leading innovations combined with our determined efforts to make the world a better place to live in. Industry should be able to sit up and take notice of the impact we make and we should strive to ensure that our students continue to become part of global corporations and governments alike. As is said - change should be from within the system by being part of it and not exclusive to the system itself. It is also very important to bear in mind that consistency is key to maintaining excellence. The fact that we are #1 in National ranking is indeed a time to rejoice but not to relax. A parallel area of focus should also be the micro-issues that impact the immediate society around us. These could be at a local level, or perhaps even at a community level. We must invest time to work on those problems and come up with feasible solutions. Giving back to society we operate in is a crucial guiding principle we must all bear in mind at all times. I re-affirm my commitment which I’ve made to ensure enhanced focus on local issues of relevance. To conclude, I once again welcome you to this great centre of learning where the world amalgamates. Let us all continue to hold the torch high of IIT Madras as we look in to the future. Prof. V. Kamakoti For JEE Advanced 2024 Aspirants Visit askiitm.com The JoSAA counselling process can be tricky. Current students and alumni of IIT Madras are here to help out! Get your doubts cleared within 1 day. Or browse through existing answers and videos about everything there is to life at IITs. Campus Life About Life on Campus Credits Dhanalakshmi Padmaraj Research Scholar, Civil Engineering Credits Niladri Ph D, Mechanical Engineering Credits V. Abhigna B Tech, Mechanical Engineering Credits Karthicanand M S MS Scholar, Management Studies IIT Madras is a vibrant residential campus that allows students to flourish both personally and professionally. Campus life at IIT Madras is not just about classrooms, libraries and labs. There are several opportunities for students to pursue their favorite activities, refine their skills and discover new talents and interests. The campus is a constant buzz of varied activities and events - academic, co-curricular and extracurricular. Photographs contributed by residents - the Institute through their lens! View Gallery Credits Sonam Tantuvoy Ph D, EWRE - Civil Engineering Credits Leena MS, Electrical Engineering Credits Vaibhav Kshirsagar Project Associate, ICE Lab - Mechanical Engineering Credits Mohamed Fouzul Aleem MS, Civil Engineering Credits Soma Gouthama Chary PhD Ocean Engineering",
  "canonical_url": "https://www.iitm.ac.in/",
  "category": "government",
  "country": "IN",
  "crawl_date": "2026-03-22T16:31:09.913492",
  "links": [
    "http://www.iitm.ac.in/academics/departments/department-of-applied-mechanics",
    "http://www.iitm.ac.in/academics/study-at-iitm/exchange-Programmes",
    "http://www.iitm.ac.in/academics/departments/department-of-humanities-and-social-sciences",
    "http://www.iitm.ac.in/announcements/summer-fellowship-2026",
    "https://mst.iitm.ac.in/bs-in-medical-sciences-engineering/",
    "http://www.iitm.ac.in/sites/default/files/Others/PM-VIDYALAXMI-NODAL-BANK-LEAFLET.pdf",
    "http://www.iitm.ac.in/announcements/crouching-tiger-report-startups-textiles",
    "http://www.iitm.ac.in/research/national-research-centres/national-cancer-tissue-biobank",
    "http://www.iitm.ac.in/announcements/79th-independence-day-celebrations-live-streaming",
    "http://www.iitm.ac.in/research/institute-research-centres/iitm-china-studies-centre",
    "http://www.iitm.ac.in/research/institute-research-centres/centre-for-railway-research",
    "http://www.iitm.ac.in/happenings/events/spectrum-inspired-low-light-image-translation-saliency-detection",
    "http://www.iitm.ac.in/academics/departments/department-of-aerospace-engineering",
    "http://www.iitm.ac.in/academics/departments/department-of-mechanical-engineering",
    "https://www.linkedin.com/school/reachiitm/",
    "http://www.iitm.ac.in/sites/default/files/Others/PG_Admissions_2025.pdf",
    "https://ge.iitm.ac.in/I2MP/",
    "http://www.iitm.ac.in/academics/departments/department-of-civil-engineering",
    "http://www.iitm.ac.in/research/institute-research-centres/international-centre-for-clean-water",
    "http://www.iitm.ac.in/research/national-research-centres/national-centre-for-combustion-research-and-development",
    "http://www.iitm.ac.in/academics/study-at-iitm/non-campus-bs-programmes",
    "http://www.iitm.ac.in/research/institute-research-centres/centre-for-nems-and-nanophotonics",
    "http://www.iitm.ac.in/happenings/press-releases-and-coverages/iit-madras-study-charts-renewable-energy-pathway-zero",
    "https://twitter.com/iitmadras",
    "http://www.iitm.ac.in/announcements/62nd-convocation",
    "http://www.iitm.ac.in/academics/departments/department-of-computer-science-engineering",
    "http://www.iitm.ac.in/academics/departments/department-of-ocean-engineering",
    "http://www.iitm.ac.in/announcements/66th-institute-day-2025-live-streaming",
    "http://www.iitm.ac.in/research-park/iitm-pravartak",
    "http://www.iitm.ac.in/research/research-highlights",
    "http://www.iitm.ac.in/research/research-highlights/why-getting-too-personal-may-harm-e-commerce",
    "http://www.iitm.ac.in/academics/departments/department-of-chemistry",
    "http://www.iitm.ac.in/happenings/press-releases-and-coverages/iit-madras-launches-postgraduate-diploma-manufacturing",
    "https://www.askiitm.com/",
    "http://www.iitm.ac.in/academics/departments/department-of-metallurgical-and-materials-engineering",
    "http://www.iitm.ac.in/sites/default/files/Others/UG_Admission_2025__2_.pdf",
    "http://www.iitm.ac.in/academics/study-at-iitm/research-programmes",
    "http://www.iitm.ac.in/innovation/gopalakrishnan-deshpande-centre-for-innovation-and-entrepreneurship",
    "https://www.facebook.com/ReachIITM",
    "http://www.iitm.ac.in/instigram-photo-gallery",
    "http://www.iitm.ac.in/academics/study-at-iitm/joint-degree-programmes",
    "https://youtube.com/user/ReachIITM",
    "http://www.iitm.ac.in/academics/departments/department-of-mathematics",
    "http://www.iitm.ac.in/announcements/vigilance-awareness-week-27th-october-2nd-november-2025-0",
    "http://www.iitm.ac.in/happenings/events",
    "http://www.iitm.ac.in/research/institute-research-centres/centre-for-computational-brain-research",
    "http://www.iitm.ac.in/research/research-centres/ttk-center-rehabilitation-research-and-device-development-r2d2",
    "http://www.iitm.ac.in/academics/departments/department-of-engineering-design",
    "http://www.iitm.ac.in/research-park/iit-madras-bioincubator",
    "http://www.iitm.ac.in/happenings/IITM-in-the-news",
    "http://www.iitm.ac.in/research/research-highlights/how-cool-motorbikes-are-choking-indian-cities",
    "http://www.iitm.ac.in/research/national-research-centres/national-technology-centre-for-ports-waterways-and-coasts",
    "http://www.iitm.ac.in/academics/departments/department-of-physics",
    "http://www.iitm.ac.in/research-park/incubation-cell",
    "http://www.iitm.ac.in/academics/departments/department-of-electrical-engineering",
    "http://www.iitm.ac.in/innovation/technology-transfer",
    "https://facapp.iitm.ac.in/",
    "http://www.iitm.ac.in/academics/departments/department-of-management-studies",
    "http://www.iitm.ac.in/research/institute-research-centres/advanced-manufacturing-technology-development-centre",
    "http://www.iitm.ac.in/academics/study-at-iitm/undergraduate-programmes",
    "http://www.iitm.ac.in/research/national-research-centres/indo-german-centre-for-sustainability",
    "http://www.iitm.ac.in/academics/departments/department-of-biotechnology",
    "http://www.iitm.ac.in/research/institute-research-centres/centre-of-excellence-in-wireless-technology",
    "http://www.iitm.ac.in/research-park/iitm-research-park",
    "http://www.iitm.ac.in/academics/departments/department-of-chemical-engineering",
    "http://www.iitm.ac.in/innovation/industrial-consultancy",
    "http://www.iitm.ac.in/research/institute-research-centres/robert-bosch-centre-for-data-science-and-artificial-intelligence",
    "http://www.iitm.ac.in/research/institute-research-centres/centre-for-technology-and-policy",
    "http://www.iitm.ac.in/research/institute-research-centres/healthcare-technology-innovation-centre",
    "http://www.iitm.ac.in/academics/study-at-iitm/international-interdisciplinary-masters-program-i2mp",
    "https://www.instagram.com/reachiitm/",
    "http://www.iitm.ac.in/announcements/vigilance-awareness-week-27th-october-2nd-november-2025",
    "http://www.iitm.ac.in/announcements/ddws-innovation-challenge-2025-26-application-portal-open-now",
    "http://www.iitm.ac.in/campus-life/overview",
    "http://www.iitm.ac.in/academics/study-at-iitm/postgraduate-programmes",
    "http://www.iitm.ac.in/happenings/press-releases-and-coverages/iit-madras-honours-six-educators-first-principles-teachers"
  ],
  "image_urls": [
    "http://www.iitm.ac.in/sites/default/files/styles/img_m2/public/2020-04/homepagetile-cancer%20tissue%20bank.jpg?itok=LaUEp5Zk",
    "http://www.iitm.ac.in/sites/default/files/2020-04/homepagetile-metallurgical.jpg",
    "http://www.iitm.ac.in/sites/default/files/styles/img_m1/public/2020-04/motor.jpg?itok=nsAfe6Bk",
    "http://www.iitm.ac.in/sites/default/files/card_images/homepagetile%20-exchange%20program1_0_0.jpg",
    "http://www.iitm.ac.in/sites/default/files/styles/img_m2/public/2020-04/homepagetile-RBCDAI.jpg?itok=jQNU1dV0",
    "http://www.iitm.ac.in/sites/default/files/styles/image_m7/public/instigram/202006/9495651909_Scholars%27%20Room-Typical%20Scholars%27%20Room.jpeg?itok=bbdVo2SS",
    "http://www.iitm.ac.in/sites/default/files/styles/image_m7/public/2020-03/campus-life-last-pic-replacement_1.jpg?itok=t7GDj3me",
    "http://www.iitm.ac.in/themes/custom/iitm/assets/images/home/campus-life/your-campus.png",
    "http://www.iitm.ac.in/sites/default/files/styles/img_m1/public/2020-04/e-commerce.jpg?itok=EXfaqCWi",
    "http://www.iitm.ac.in/sites/default/files/2020-04/homepagetile-Math.jpg",
    "http://www.iitm.ac.in/sites/default/files/2020-04/homepagetile-bioincubator.jpg",
    "http://www.iitm.ac.in/sites/default/files/card_images/ask_iitm.png",
    "http://www.iitm.ac.in/sites/default/files/2020-04/homepagetile-Management.jpg",
    "http://www.iitm.ac.in/sites/default/files/card_images/ug-programmes_1_0.png",
    "http://www.iitm.ac.in/sites/default/files/styles/img_m2/public/2020-04/homepagetile-igcs.jpg?itok=d5DXk_xf",
    "http://www.iitm.ac.in/sites/default/files/styles/img_s7/public/instigram/202006/9790712203_Tunga%20hostel%20%283%29.jpeg?itok=EiEmy4MU",
    "http://www.iitm.ac.in/sites/default/files/2020-04/homepagetile-humanities.jpg",
    "http://www.iitm.ac.in/sites/default/files/2020-04/industrial-consultancy.png",
    "http://www.iitm.ac.in/sites/default/files/2020-08/homepagetile-gdc1.jpg",
    "http://www.iitm.ac.in/sites/default/files/2020-04/biotechnology.jpg",
    "http://www.iitm.ac.in/sites/default/files/styles/img_m2/public/2022-04/Shailesh%202.png?itok=7qxmglk2",
    "http://www.iitm.ac.in/sites/default/files/2020-04/chemistry.jpg",
    "http://www.iitm.ac.in/sites/default/files/card_images/homepagetile-joint%20degree%20programme_0_0.jpg",
    "http://www.iitm.ac.in/sites/default/files/2020-04/homepagetile-Computer%20Sciences%20Block%20IMG_7549.jpg",
    "http://www.iitm.ac.in/sites/default/files/2020-04/homepagetile-mechanical.jpg",
    "http://www.iitm.ac.in/sites/default/files/2024-12/single-img-16_0.jpg",
    "http://www.iitm.ac.in/sites/default/files/styles/img_s5/public/happenings/press_release/pressrelease26_02_2026_14_28.jpg?itok=ZeRflvjZ",
    "http://www.iitm.ac.in/sites/default/files/card_images/innovation4.png",
    "http://www.iitm.ac.in/sites/default/files/styles/img_m2/public/2020-04/homepagetile-HTIC_0.jpg?itok=t9fqpTE-",
    "http://www.iitm.ac.in/sites/default/files/styles/image_m7/public/instigram/202006/9941257919_Open%20Air%20Theatre%20-%20Alladin.jpeg?itok=4VdPNAaT",
    "http://www.iitm.ac.in/sites/default/files/styles/img_s7/public/instigram/202006/9500737891_Deer%20-%20WhatsApp%20Image%202019-12-10%20at%201.50.53%20PM%20%281%29.jpeg?itok=UIYnn3XA",
    "http://www.iitm.ac.in/sites/default/files/styles/img_m2/public/2020-08/homepagetile-AMTDC_0.jpg?itok=ZMmchkvX",
    "http://www.iitm.ac.in/sites/default/files/2020-04/homepagetile-aerospace.jpg",
    "http://www.iitm.ac.in/sites/default/files/styles/image_m7/public/instigram/202006/8106734686_Shopping%20complex%20%282%29.jpeg?itok=eZF-906g",
    "http://www.iitm.ac.in/sites/default/files/2020-04/homepagetile-Civil%20dept.jpg",
    "http://www.iitm.ac.in/sites/default/files/styles/img_m2/public/2020-08/homepagetile-ntcpwc.jpg?itok=WaEsh4FW",
    "http://www.iitm.ac.in/sites/default/files/styles/img_m2/public/2020-04/homepagetile-railway%20research.jpg?itok=-oUufYhz",
    "http://www.iitm.ac.in/sites/default/files/styles/img_m2/public/2020-08/homepagetile-China%20Studies.jpg?itok=U3B_z_T0",
    "http://www.iitm.ac.in/sites/default/files/2020-04/homepagetile-applied%20mechanics.jpg",
    "http://www.iitm.ac.in/sites/default/files/styles/img_m2/public/2020-04/homepagetile-header%20CTAP_1.jpg?itok=fDMOs2SX",
    "http://www.iitm.ac.in/sites/default/files/2020-04/homepagetile-Chem%20dept.jpg",
    "http://www.iitm.ac.in/sites/default/files/card_images/research-programmes_1_0.png",
    "http://www.iitm.ac.in/sites/default/files/2020-04/homepagetile-ocean%20engg.jpg",
    "http://www.iitm.ac.in/sites/default/files/styles/image_m7/public/instigram/202006/9635020772_Library%20inside%20%282%29.jpeg?itok=8J3thurD",
    "http://www.iitm.ac.in/sites/default/files/2020-04/homepagetile-physics.jpg",
    "http://www.iitm.ac.in/sites/default/files/styles/img_m2/public/2020-04/homepagetile-NCCRD_0.jpg?itok=TlEC7l2d",
    "http://www.iitm.ac.in/sites/default/files/2020-06/homepagetile-researchpark.jpg",
    "http://www.iitm.ac.in/sites/default/files/styles/img_m2/public/2020-04/homepagetile-NEMS.jpg?itok=2414xqIz",
    "http://www.iitm.ac.in/sites/default/files/2020-04/homepagetile-technology%20transfer.jpg",
    "http://www.iitm.ac.in/sites/default/files/styles/img_s7/public/instigram/202006/7588402025_Water%20Tank%209.jpeg?itok=PswG5cw7",
    "http://www.iitm.ac.in/sites/default/files/styles/img_s7/public/instigram/202006/9951320474_WhatsApp%20Image%202020-06-05%20at%207.07.44%20AM.jpeg?itok=HIanpJEs",
    "http://www.iitm.ac.in/sites/default/files/2020-04/engineering.jpg",
    "http://www.iitm.ac.in/sites/default/files/2022-01/Director-Best_Resized_0.png",
    "http://www.iitm.ac.in/sites/default/files/card_images/homepagetile-onlineBscprogram.jpg",
    "http://www.iitm.ac.in/sites/default/files/styles/img_s5/public/happenings/press_release/pressrelease09_03_2026_16_49.jpg?itok=4xcFD7M8",
    "http://www.iitm.ac.in/sites/default/files/card_images/pg-programmes_1_0.png",
    "http://www.iitm.ac.in/sites/default/files/styles/img_m2/public/2020-08/homepagetile-Cewit.jpg?itok=zAIxIhi1",
    "http://www.iitm.ac.in/sites/default/files/2020-04/homepagetile-Electrical%20Sciences%20Block%20IMG_7657.jpg",
    "http://www.iitm.ac.in/sites/default/files/styles/img_m6/public/instigram/202005/Administration-Academic%20Administration.jpg?itok=iR1mdQKl",
    "http://www.iitm.ac.in/sites/default/files/styles/img_m2/public/2020-04/homepagetile-ccbr_0.jpg?itok=mogUlUcu",
    "http://www.iitm.ac.in/sites/default/files/styles/img_m2/public/2020-08/homepagetile-iccw.jpg?itok=X-mypUbV",
    "http://www.iitm.ac.in/sites/default/files/2020-04/homepagetile-incubation%20cell.jpg",
    "http://www.iitm.ac.in/sites/default/files/styles/img_s5/public/happenings/press_release/pressrelease05_03_2026_17_14.jpg?itok=8YCqLGrM"
  ],
  "headings": {
    "h1": [
      "No. 1 for 5 Years Running..."
    ],
    "h2": [
      "The Champions of Technology",
      "Incubating Minds",
      "Catalyzing Careers",
      "The Best of the Best",
      "No. 1 for 9 Years Running...",
      "News",
      "Recent",
      "Study @ IITM",
      "Research",
      "Departments",
      "Consultancy & Innovation",
      "IIT Madras by the Numbers",
      "Message from the Director"
    ],
    "h3": [
      "IIT Madras honours six educators with First Principles Teachers Award 2026",
      "IIT Madras launches Postgraduate Diploma in Manufacturing Analytics for Industry…",
      "IIT Madras study charts renewable energy pathway for Zero-Emission Trucking",
      "Spectrum Inspired Low-light Image Translation for Saliency Detection",
      "Online BSc Programme",
      "Undergraduate Programmes",
      "Postgraduate Programmes",
      "Research Programmes",
      "International Masters’ Program",
      "Exchange Programmes",
      "Joint Degree Programmes",
      "Highlights",
      "Centres",
      "Aerospace Engineering",
      "Applied Mechanics & Biomedical Engineering",
      "Biotechnology",
      "Chemical Engineering",
      "Chemistry",
      "Civil Engineering",
      "Computer Science & Engineering",
      "Electrical Engineering",
      "Engineering Design",
      "Humanities and Social Sciences",
      "Management Studies",
      "Mathematics",
      "Mechanical Engineering",
      "Metallurgical and Materials Engineering",
      "Ocean Engineering",
      "Physics",
      "Industrial Consultancy",
      "Incubation Cell",
      "IIT Madras Bioincubator",
      "IITM Research Park",
      "Technology Transfer",
      "Gopalakrishnan-Deshpande Centre",
      "IITM Pravartak",
      "2,105",
      "4,112",
      "746",
      "2,963",
      "591",
      "677",
      "146",
      "829",
      "Prof. V. Kamakoti"
    ],
    "h4": [
      "How cool motorbikes are choking Indian cities!",
      "Why getting too personal may harm e-Commerce!",
      "Healthcare Technology Innovation Centre (HTIC)",
      "Centre for Technology and Policy (CTaP)",
      "National Technology Centre for Ports, Waterways and Coasts (NTCPWC)",
      "IITM China Studies Centre",
      "Advanced Manufacturing Technology Development Centre (AMTDC)",
      "National Centre for Combustion Research and Development (NCCRD)",
      "National Cancer Tissue Biobank (NCTB)",
      "Centre of Excellence in Wireless Technology (CEWiT)",
      "Centre for Computational Brain Research",
      "Centre for Railway Research",
      "Centre for NEMS and Nanophotonics (CNNP)",
      "International Centre for Clean Water (ICCW)",
      "TTK Center for Rehabilitation Research and Device Development (R2D2)",
      "Indo-German Centre for Sustainability",
      "Robert Bosch Centre for Data Science and Artificial Intelligence",
      "For JEE Advanced 2024 Aspirants",
      "Campus Life"
    ],
    "h5": [],
    "h6": []
  },
  "word_count": 1759,
  "link_count": 76,
  "image_count": 63
}